{"business_discovery":{"media":{"data":[{"id":"17892301250698875","media_url":"https:\/\/scontent.cdninstagram.com\/v\/t51.29350-15\/327304299_594871809146377_2934785846516861908_n.jpg?_nc_cat=102&ccb=1-7&_nc_sid=8ae9d6&_nc_ohc=teayo6g6AIMAX9KRzoh&_nc_ht=scontent.cdninstagram.com&edm=AL-3X8kEAAAA&oh=00_AfCBLQzcf_xVEHh3jhmIGXxoDAq_OoycXJujBQyS0XK9JA&oe=63D995A0","permalink":"https:\/\/www.instagram.com\/p\/Cn1bp3jvzew\/","media_type":"CAROUSEL_ALBUM"},{"id":"17941152251424082","media_url":"https:\/\/scontent.cdninstagram.com\/v\/t51.29350-15\/326447410_222993433483587_2904333225835758194_n.jpg?_nc_cat=105&ccb=1-7&_nc_sid=8ae9d6&_nc_ohc=BiRSEPJVRkAAX-N14eH&_nc_ht=scontent.cdninstagram.com&edm=AL-3X8kEAAAA&oh=00_AfDMlBLa5gVDSpFVRNBZITINY59hrMYF8Osm061lT24zZA&oe=63D96C7F","permalink":"https:\/\/www.instagram.com\/p\/CnwPXxfPmME\/","media_type":"CAROUSEL_ALBUM"},{"id":"18013324252510603","media_url":"https:\/\/scontent.cdninstagram.com\/v\/t51.29350-15\/326493115_1598211943933375_7638171283791054730_n.jpg?_nc_cat=100&ccb=1-7&_nc_sid=8ae9d6&_nc_ohc=WEcdq8BRB1cAX9rpQta&_nc_ht=scontent.cdninstagram.com&edm=AL-3X8kEAAAA&oh=00_AfCe0-E0dFKIm-RTMzzFWld7EWcGeCTM-GNZsaShhi6t6w&oe=63D7CF8A","permalink":"https:\/\/www.instagram.com\/p\/CnrU6nTPd3M\/","media_type":"CAROUSEL_ALBUM"},{"id":"18077826199333328","media_url":"https:\/\/scontent.cdninstagram.com\/v\/t51.29350-15\/326143952_158971570246283_6699814904742261524_n.jpg?_nc_cat=103&ccb=1-7&_nc_sid=8ae9d6&_nc_ohc=WRKtRhB-6DkAX_ryjJA&_nc_ht=scontent.cdninstagram.com&edm=AL-3X8kEAAAA&oh=00_AfBLlb8CqL2kN9IxT-IHnQiohjYj4DV-coGzxnfIunVs5Q&oe=63D96809","permalink":"https:\/\/www.instagram.com\/p\/Cnoxrv4P2ZH\/","media_type":"CAROUSEL_ALBUM"},{"id":"17956043078188059","media_url":"https:\/\/scontent.cdninstagram.com\/v\/t51.29350-15\/326126554_682818430210158_2432578243261741663_n.jpg?_nc_cat=102&ccb=1-7&_nc_sid=8ae9d6&_nc_ohc=sxPK8yDlFsQAX9HSZEe&_nc_ht=scontent.cdninstagram.com&edm=AL-3X8kEAAAA&oh=00_AfAY0Uw6vmRUhm-CjFYG9neqfhN_uxuKZzU4JKtMDfdAxg&oe=63D8AC93","permalink":"https:\/\/www.instagram.com\/p\/CnmWTmaPs2P\/","media_type":"CAROUSEL_ALBUM"},{"id":"18193135453218527","media_url":"https:\/\/scontent.cdninstagram.com\/v\/t51.29350-15\/325770590_715126506877293_3507104775830205594_n.jpg?_nc_cat=103&ccb=1-7&_nc_sid=8ae9d6&_nc_ohc=TEhpTodMOEsAX_WBvku&_nc_ht=scontent.cdninstagram.com&edm=AL-3X8kEAAAA&oh=00_AfDZb13FiM_6SKm71XAfF9k1BNBj9B7RcE3os2u11BOmBA&oe=63D83434","permalink":"https:\/\/www.instagram.com\/p\/CnjrQU2PUgf\/","media_type":"CAROUSEL_ALBUM"},{"id":"17970844988079611","media_url":"https:\/\/scontent.cdninstagram.com\/v\/t51.29350-15\/325705789_856370202249113_7667122318739460289_n.jpg?_nc_cat=111&ccb=1-7&_nc_sid=8ae9d6&_nc_ohc=Y_c4DvvZQwsAX9J7U6_&_nc_ht=scontent.cdninstagram.com&edm=AL-3X8kEAAAA&oh=00_AfAYTybM2DdztkOFeS0f9-WISMaRTth-qiznKQOc6qeVBQ&oe=63D8C98E","permalink":"https:\/\/www.instagram.com\/p\/CnhOluMPHgP\/","media_type":"CAROUSEL_ALBUM"},{"id":"17991814768710205","media_url":"https:\/\/scontent.cdninstagram.com\/v\/t51.29350-15\/325671443_683856460048834_8584419671267955233_n.jpg?_nc_cat=107&ccb=1-7&_nc_sid=8ae9d6&_nc_ohc=xNxEfh-bNYsAX_4Aiw_&_nc_ht=scontent.cdninstagram.com&edm=AL-3X8kEAAAA&oh=00_AfBOyVK-Tqww9ID8Ji9-EHg10FPUybBxfwwHcTh-LRCOXQ&oe=63D98C6E","permalink":"https:\/\/www.instagram.com\/p\/Cnb3zbHvCMN\/","media_type":"CAROUSEL_ALBUM"},{"id":"18071225011341913","media_url":"https:\/\/scontent.cdninstagram.com\/v\/t51.29350-15\/321609294_733624341446303_3959909022312978891_n.jpg?_nc_cat=107&ccb=1-7&_nc_sid=8ae9d6&_nc_ohc=11UymZW4uMcAX8Fy2Xd&_nc_ht=scontent.cdninstagram.com&edm=AL-3X8kEAAAA&oh=00_AfBq0OBPriNjMYJ-MvSTi4FGcyLyv8_N9-PdAKPWfPDDpA&oe=63D7D8E7","permalink":"https:\/\/www.instagram.com\/p\/CnZaJJzvJIi\/","media_type":"CAROUSEL_ALBUM"},{"id":"17865753140842545","media_url":"https:\/\/scontent.cdninstagram.com\/v\/t51.29350-15\/325174503_874718907181188_4860093367094300115_n.jpg?_nc_cat=100&ccb=1-7&_nc_sid=8ae9d6&_nc_ohc=se8TTuWPwtEAX85lUA5&_nc_ht=scontent.cdninstagram.com&edm=AL-3X8kEAAAA&oh=00_AfDuJVrYcsI6IqQ-MqrHtLXUY9-VfPpS6ZIJcaUmgr5crQ&oe=63D86E08","permalink":"https:\/\/www.instagram.com\/p\/CnT_VyXPlRZ\/","media_type":"CAROUSEL_ALBUM"},{"id":"17966568179301848","media_url":"https:\/\/scontent.cdninstagram.com\/v\/t51.29350-15\/324571685_840106200411120_1162334444336384711_n.jpg?_nc_cat=107&ccb=1-7&_nc_sid=8ae9d6&_nc_ohc=nBDlKnnqCuIAX92xg1I&_nc_ht=scontent.cdninstagram.com&edm=AL-3X8kEAAAA&oh=00_AfA8dzNMBWds3LA6fvC0L387K4gYJb0d9CSEP_W7g4n7lA&oe=63D8A42C","permalink":"https:\/\/www.instagram.com\/p\/CnRppV7PeEz\/","media_type":"CAROUSEL_ALBUM"},{"id":"17842764479923206","media_url":"https:\/\/scontent.cdninstagram.com\/v\/t51.29350-15\/324381329_212876497766064_5237336942901664803_n.jpg?_nc_cat=100&ccb=1-7&_nc_sid=8ae9d6&_nc_ohc=99ZcOIoLODsAX9W5ome&_nc_ht=scontent.cdninstagram.com&edm=AL-3X8kEAAAA&oh=00_AfAITjBiZhstsvblIdxaAl3m0hqUwLZQCAjcVNfFyqYRDA&oe=63D99247","permalink":"https:\/\/www.instagram.com\/p\/CnOzC7uP3P5\/","media_type":"CAROUSEL_ALBUM"},{"id":"18265484374139797","media_url":"https:\/\/scontent.cdninstagram.com\/v\/t51.29350-15\/321915820_932638004813667_2496855278607619057_n.jpg?_nc_cat=108&ccb=1-7&_nc_sid=8ae9d6&_nc_ohc=Rr3wTrmUy_EAX-BREfh&_nc_ht=scontent.cdninstagram.com&edm=AL-3X8kEAAAA&oh=00_AfDsOSJfwdGVuQb3rqBbsytymPbJ3q_x1gikQaF-DuSAGw&oe=63D7F178","permalink":"https:\/\/www.instagram.com\/p\/CmofI9pvV1h\/","media_type":"CAROUSEL_ALBUM"},{"id":"18236607595157200","media_url":"https:\/\/scontent.cdninstagram.com\/v\/t51.29350-15\/321925560_209321904962973_4273702590327966889_n.jpg?_nc_cat=102&ccb=1-7&_nc_sid=8ae9d6&_nc_ohc=KDChAtOoWSoAX-NPmmb&_nc_ht=scontent.cdninstagram.com&edm=AL-3X8kEAAAA&oh=00_AfA_7vTX5nIC6qK7LRBrv1hQVAB1Pl2XsIqskEFUy4W1_Q&oe=63D9462D","permalink":"https:\/\/www.instagram.com\/p\/CmjagYOPHMs\/","media_type":"CAROUSEL_ALBUM"},{"id":"17985345811742438","media_url":"https:\/\/scontent.cdninstagram.com\/v\/t51.29350-15\/321184505_477415437859945_5211521519322753090_n.jpg?_nc_cat=109&ccb=1-7&_nc_sid=8ae9d6&_nc_ohc=RdUPfTW9dLQAX8SW4Qt&_nc_ht=scontent.cdninstagram.com&edm=AL-3X8kEAAAA&oh=00_AfAdNvmrnu3GZpacCzGD7YvMgoboKkfnSSqoj6l7JPL4Jw&oe=63D845A1","permalink":"https:\/\/www.instagram.com\/p\/Cmg02oOvvj8\/","media_type":"CAROUSEL_ALBUM"},{"id":"17999957470576358","media_url":"https:\/\/scontent.cdninstagram.com\/v\/t51.29350-15\/320701699_176900988279308_4524877016001565191_n.jpg?_nc_cat=103&ccb=1-7&_nc_sid=8ae9d6&_nc_ohc=c_iHu2uQFXwAX8CgXeU&_nc_ht=scontent.cdninstagram.com&edm=AL-3X8kEAAAA&oh=00_AfAoTPnP4rdkelrnNw6RuP3SXd1mOu1PKgPRkZ5K_JsorA&oe=63D956F7","permalink":"https:\/\/www.instagram.com\/p\/CmbY-yvvSax\/","media_type":"CAROUSEL_ALBUM"},{"id":"17956162874115560","media_url":"https:\/\/scontent.cdninstagram.com\/v\/t51.29350-15\/321178423_560320192212170_7018378387511230059_n.jpg?_nc_cat=102&ccb=1-7&_nc_sid=8ae9d6&_nc_ohc=JoA6FeueetgAX85isP4&_nc_ht=scontent.cdninstagram.com&edm=AL-3X8kEAAAA&oh=00_AfDFK4m1QAGWif9F9JSC6r_--zU4nCPgRO_QM6-Cle7VmQ&oe=63D8905A","permalink":"https:\/\/www.instagram.com\/p\/CmZHaxhvKAk\/","media_type":"CAROUSEL_ALBUM"},{"id":"17991829786650198","media_url":"https:\/\/scontent.cdninstagram.com\/v\/t51.29350-15\/320397905_1190551428535909_3872104677309111347_n.jpg?_nc_cat=110&ccb=1-7&_nc_sid=8ae9d6&_nc_ohc=zdW_JCw1tawAX_JAgFi&_nc_ht=scontent.cdninstagram.com&edm=AL-3X8kEAAAA&oh=00_AfBa8_OwfLK0XxMiKGXrsDj1wr6BlQy0qZZpSKjpr92V6w&oe=63D916E4","permalink":"https:\/\/www.instagram.com\/p\/CmWVzTAPQlm\/","media_type":"CAROUSEL_ALBUM"},{"id":"17980500802834178","media_url":"https:\/\/scontent.cdninstagram.com\/v\/t51.29350-15\/320357345_1273704473212870_7549319772402254893_n.jpg?_nc_cat=107&ccb=1-7&_nc_sid=8ae9d6&_nc_ohc=fPjptekg_MMAX9bMIdm&_nc_ht=scontent.cdninstagram.com&edm=AL-3X8kEAAAA&oh=00_AfACS7_p4TPptHjReR_RN940iIpON-AdEL5oMCYRJFTVTw&oe=63D88D1F","permalink":"https:\/\/www.instagram.com\/p\/CmTzBbyvUNB\/","media_type":"CAROUSEL_ALBUM"},{"id":"18194090482234176","media_url":"https:\/\/scontent.cdninstagram.com\/v\/t51.29350-15\/319333379_445396797783066_2039759473310809706_n.jpg?_nc_cat=101&ccb=1-7&_nc_sid=8ae9d6&_nc_ohc=Qjf_xmCGaokAX_ajZoD&_nc_ht=scontent.cdninstagram.com&edm=AL-3X8kEAAAA&oh=00_AfBSfsnHMN6StYu5MzjoK8xv2sTfLwLcFBJihBC958xUSA&oe=63D8E64A","permalink":"https:\/\/www.instagram.com\/p\/Cl8ayTvv8D8\/","media_type":"CAROUSEL_ALBUM"},{"id":"17965650083082322","media_url":"https:\/\/scontent.cdninstagram.com\/v\/t51.29350-15\/318682935_1052185482844250_8261043803135486584_n.jpg?_nc_cat=109&ccb=1-7&_nc_sid=8ae9d6&_nc_ohc=Uuxc15fYNF4AX91jYTl&_nc_ht=scontent.cdninstagram.com&edm=AL-3X8kEAAAA&oh=00_AfCMKeS0e-9qiBdQ51PqDslmrsHHazh0XSuVwb2LOpDoRQ&oe=63D80046","permalink":"https:\/\/www.instagram.com\/p\/Cl6KCZ4P35A\/","media_type":"CAROUSEL_ALBUM"},{"id":"17849583917861151","media_url":"https:\/\/scontent.cdninstagram.com\/v\/t51.29350-15\/317365254_826736661865807_5712620695964131823_n.jpg?_nc_cat=111&ccb=1-7&_nc_sid=8ae9d6&_nc_ohc=h635dVWjLnEAX_Yc4Fc&_nc_ht=scontent.cdninstagram.com&edm=AL-3X8kEAAAA&oh=00_AfDHfArm-qV2Q1zNyKejHCqy9dlGL-2jKZ5FMqHl0envag&oe=63D99F92","permalink":"https:\/\/www.instagram.com\/p\/CljBd8Sv2zh\/","media_type":"CAROUSEL_ALBUM"},{"id":"17889076628740701","media_url":"https:\/\/scontent.cdninstagram.com\/v\/t51.29350-15\/317012607_501498591943052_9096575093576782057_n.jpg?_nc_cat=108&ccb=1-7&_nc_sid=8ae9d6&_nc_ohc=Phs2tZUCDu0AX-Wz6Zd&_nc_ht=scontent.cdninstagram.com&edm=AL-3X8kEAAAA&oh=00_AfC7yAR2M23xjFk2UPsK9NItwjwu8et3ZP781dRAPC5h6Q&oe=63D8B727","permalink":"https:\/\/www.instagram.com\/p\/ClgCoaXPeZs\/","media_type":"CAROUSEL_ALBUM"},{"id":"17933338496533380","media_url":"https:\/\/scontent.cdninstagram.com\/v\/t51.29350-15\/316535082_809774880128002_1258347990710441962_n.jpg?_nc_cat=110&ccb=1-7&_nc_sid=8ae9d6&_nc_ohc=MtAgtEhFrNwAX9mCxIK&_nc_ht=scontent.cdninstagram.com&edm=AL-3X8kEAAAA&oh=00_AfAIcP57gXJS4kvIxO5tisSKNFZgbKV2wsSkcPZyJUFE-Q&oe=63D93C91","permalink":"https:\/\/www.instagram.com\/p\/ClWDW2fPJSd\/","media_type":"CAROUSEL_ALBUM"},{"id":"17912446778578960","media_url":"https:\/\/scontent.cdninstagram.com\/v\/t51.29350-15\/316641571_681361490285997_3619506850581965819_n.jpg?_nc_cat=109&ccb=1-7&_nc_sid=8ae9d6&_nc_ohc=rXp9ypWS0hQAX9ItuSp&_nc_ht=scontent.cdninstagram.com&edm=AL-3X8kEAAAA&oh=00_AfBEOT3pcQzFM164oCEX0Thrd41foSLHl_iwGlcnCQnNPw&oe=63D7DA79","permalink":"https:\/\/www.instagram.com\/p\/ClS_YybvUxG\/","media_type":"CAROUSEL_ALBUM"}],"paging":{"cursors":{"after":"QVFIUjdLOU1jbEhndGE1Qy1aaFk5a1JoWlRXUHpiMXJiSXBjcjVNSGNZAMVNSZAlF1VDFEMVU0TVJkRjN4M0ZAPZAEhfc2loblhVZAHVRcjMzX2pXR1A4VVNvVjNR"}}},"id":"17841406937882405"},"id":"17841457502307817"}